optseq_trial/__init__.py
optseq_trial/optseq-linux
optseq_trial/optseq-mac
optseq_trial/optseq.exe
optseq_trial/optseq.py
optseq_trial/py.typed
optseq_trial/data/ft06.txt
optseq_trial/data/ft10.txt
optseq_trial/data/ft20.txt
optseq_trial-0.1.1.dist-info/METADATA
optseq_trial-0.1.1.dist-info/WHEEL
optseq_trial-0.1.1.dist-info/licenses/LICENSE
optseq_trial-0.1.1.dist-info/RECORD
