Metadata-Version: 2.4
Name: optseq-trial
Version: 0.1.1
Summary: Optseq trial version.
Author-email: Mikio Kubo <kubo@kaiyodai.ac.jp>, Saito Tsutomu <tsutomu7@hotmail.co.jp>
License-File: LICENSE
Requires-Python: >=3.10
Requires-Dist: pydantic>=2.10.5
Provides-Extra: all
Requires-Dist: pandas; extra == 'all'
Requires-Dist: plotly; extra == 'all'
